huey_email/__init__.py
huey_email/backends.py
huey_email/models.py
django_huey_email-0.0.1.dist-info/LICENSE
django_huey_email-0.0.1.dist-info/METADATA
django_huey_email-0.0.1.dist-info/WHEEL
django_huey_email-0.0.1.dist-info/RECORD
