Metadata-Version: 2.1
Name: django-huey-email
Version: 0.0.1
Summary: Asynchronous Email Backend for Django with Huey.
Home-page: https://github.com/jukanntenn/django-huey-email
License: BSD-3-Clause
Keywords: django,huey,email
Author: jukanntenn
Author-email: jukanntenn@outlook.com
Requires-Python: >=3.8,<4.0
Classifier: License :: OSI Approved :: BSD License
Classifier: Programming Language :: Python :: 3
Classifier: Programming Language :: Python :: 3.8
Classifier: Programming Language :: Python :: 3.9
Classifier: Programming Language :: Python :: 3.10
Classifier: Programming Language :: Python :: 3.11
Classifier: Programming Language :: Python :: 3.12
Requires-Dist: huey (>=2.5.0,<3.0.0)
Project-URL: Repository, https://github.com/jukanntenn/django-huey-email
